[
    {
        "label": "oven",
        "centroid_xy": [
            -87.641,
            -103.311
        ]
    },
    {
        "label": "stove",
        "centroid_xy": [
            -87.592,
            -103.889
        ]
    },
    {
        "label": "cabinet",
        "centroid_xy": [
            -42.466,
            -100.229
        ]
    },
    {
        "label": "cabinet",
        "centroid_xy": [
            19.425,
            -86.965
        ]
    },
    {
        "label": "cabinet",
        "centroid_xy": [
            99.79,
            -87.694
        ]
    },
    {
        "label": "table",
        "centroid_xy": [
            151.454,
            -81.014
        ]
    },
    {
        "label": "sink",
        "centroid_xy": [
            -2.141,
            -84.06
        ]
    },
    {
        "label": "sink",
        "centroid_xy": [
            36.557,
            -80.807
        ]
    },
    {
        "label": "cabinet",
        "centroid_xy": [
            -69.283,
            -121.941
        ]
    },
    {
        "label": "cabinet",
        "centroid_xy": [
            31.53,
            -96.921
        ]
    },
    {
        "label": "cabinet",
        "centroid_xy": [
            124.372,
            -106.512
        ]
    },
    {
        "label": "table",
        "centroid_xy": [
            -29.838,
            83.088
        ]
    },
    {
        "label": "cabinet",
        "centroid_xy": [
            34.972,
            88.107
        ]
    },
    {
        "label": "refrigerator",
        "centroid_xy": [
            95.608,
            80.116
        ]
    }
]